lmod/__init__.py
lmod/module.py
lmod/moduleloadtest.py
lmod/spider.py
lmod/__pycache__/__init__.cpython-37.pyc
lmod/__pycache__/module.cpython-37.pyc
lmod/__pycache__/moduleloadtest.cpython-37.pyc
lmod/__pycache__/spider.cpython-37.pyc
lmodule-0.4.0.dist-info/LICENSE
lmodule-0.4.0.dist-info/METADATA
lmodule-0.4.0.dist-info/WHEEL
lmodule-0.4.0.dist-info/top_level.txt
lmodule-0.4.0.dist-info/RECORD
