Metadata-Version: 2.1
Name: lmodule
Version: 0.4.0
Summary: Lmod Module API
Home-page: https://github.com/buildtesters/lmodule
Author: Shahzeb Siddiqui
Author-email: shahzebmsiddiqui@gmail.com
License: MIT
Project-URL: Source Code, https://github.com/buildtesters/lmodule
Project-URL: Documentation, https://lmodule.readthedocs.io/
Project-URL: Bug Report, https://github.com/buildtesters/lmodule/issues
Platform: UNKNOWN
Classifier: Development Status :: 3 - Alpha
Classifier: Intended Audience :: Developers
Classifier: Intended Audience :: System Administrators
Classifier: License :: OSI Approved :: MIT License
Classifier: Operating System :: POSIX :: Linux
Classifier: Programming Language :: Python :: 3.6
Classifier: Programming Language :: Python :: 3.8
Classifier: Programming Language :: Python :: 3.9
Classifier: Programming Language :: Python :: 3.10
Classifier: Topic :: Software Development :: Libraries
Requires-Python: >=3.6, <4
